personal_cloud_client/__init__.py
personal_cloud_client/cli.py
personal_cloud_client-0.0.2.dist-info/METADATA
personal_cloud_client-0.0.2.dist-info/WHEEL
personal_cloud_client-0.0.2.dist-info/entry_points.txt
personal_cloud_client-0.0.2.dist-info/RECORD
